setup.py
django_korektor.egg-info/PKG-INFO
django_korektor.egg-info/SOURCES.txt
django_korektor.egg-info/dependency_links.txt
django_korektor.egg-info/requires.txt
django_korektor.egg-info/top_level.txt
djkorektor/__init__.py
djkorektor/models.py
djkorektor/settings.py
djkorektor/urls.py
djkorektor/wsgi.py
djkorektor/management/__init__.py
djkorektor/management/commands/__init__.py
djkorektor/management/commands/djkorektor.py
djkorektor/sql/__init__.py
djkorektor/sql/bigram.sql
djkorektor/sql/locale.sql
djkorektor/sql/word.sql
djkorektor/sql/wordbigram.sql
djkorektor/sql/wordpair.sql