Metadata-Version: 1.1
Name: django-korektor
Version: 0.1.5
Summary: Google like "Did you mean" spellcheck proof of concept for Django app.
Home-page: http://github.com/pista329/django-korektor
Author: Stefan Backor
Author-email: stefan@backor.sk
License: MIT
Platform: UNKNOWN
Classifier: Programming Language :: Python
Classifier: Programming Language :: Python :: 2.7
Classifier: Programming Language :: Python :: 3.3
Classifier: Programming Language :: Python :: 3.4
Classifier: Topic :: Software Development :: Libraries :: Python Modules
Classifier: Framework :: Django
Classifier: Environment :: Web Environment
Classifier: Operating System :: OS Independent
Classifier: Natural Language :: English
